.travis.yml
LICENSE
MANIFEST.in
README.md
requirements.txt
setup.py
datasetstore/__init__.py
datasetstore/api.py
datasetstore/backend.py
datasetstore/config.py
datasetstore/error.py
datasetstore/message.py
datasetstore/repo.py
datasetstore/type.py
datasetstore.egg-info/PKG-INFO
datasetstore.egg-info/SOURCES.txt
datasetstore.egg-info/dependency_links.txt
datasetstore.egg-info/entry_points.txt
datasetstore.egg-info/requires.txt
datasetstore.egg-info/top_level.txt
datasetstore/command/__init__.py
datasetstore/command/main.py
datasetstore/command/sync_datasets.py
datasetstore/eda/__init__.py
datasetstore/eda/profiling.yml
datasetstore/eda/text.py
datasetstore/eda/video.py
datasetstore/preprocess/__init__.py
datasetstore/preprocess/text/__init__.py
datasetstore/preprocess/text/hanzi.py
datasetstore/preprocess/text/rule_pattern.py
datasetstore/preprocess/text/cleaner/__init__.py
datasetstore/preprocess/text/cleaner/emoji.py
datasetstore/preprocess/text/cleaner/extractor.py
datasetstore/preprocess/text/tokenizer/__init__.py
datasetstore/preprocess/text/tokenizer/chinese.py
datasetstore/preprocess/text/tokenizer/pretokenizer.py
datasetstore/util/__init__.py
datasetstore/util/configuration.py
datasetstore/util/log.py
datasetstore/util/option.py
datasetstore/util/process.py
datasetstore/util/python.py
datasetstore/util/regex.py
datasetstore/util/s3.py
datasetstore/util/strings.py
datasetstore/util/thread.py
datasetstore/util/tool.py
datasetstore/util/track.py