Metadata-Version: 2.1
Name: datasetstore
Version: 1.0.1.7
Summary: datasetstore 快速下载中文数据集，处理数据集，数据分析、可视化分析，一站式解决数据问题
Home-page: https://github.com/CYang828/datasetstore
Author: CYang
Author-email: zhangchunyang_pri@126.com
License: UNKNOWN
Platform: UNKNOWN
License-File: LICENSE
